.gitignore
.gitlab-ci.yml
.gitlab-pipeline-notify.yml
.gitlab-release-branch.yml
.gitlab-variables.yml
.readthedocs.yaml
LICENSE.rst
README.rst
README_doc_map.jpg
pip_common.sh
publish.settings.sh
publish.sh
pyproject.toml
.idea/modules.xml
.idea/peek.iml
.idea/inspectionProfiles/Project_Default.xml
.idea/inspectionProfiles/profiles_settings.xml
ci/base.yml
ci/peek-git-clone-repos.yml
ci/peek-git-sha1-doc.yml
ci/peek-linux-dependencies-fetch.yml
ci/peek-linux-package-build.yml
ci/peek-linux-package-test.yml
ci/peek-linux-package-upload.yml
ci/peek-py-package-build.yml
ci/peek-py-package-md5-doc.yml
ci/peek-py-package-upload.yml
ci/peek-sbom-generation.yml
ci/admin/dump_config_only.sh
ci/admin/p_gen_self_signed_certificates.py
ci/admin/p_gen_self_signed_certificates.sh
ci/admin/update_app_server.sql
ci/pkg-scripts/verify-installation.sh
ci/profile.d/901-peek-platform.sh
ci/scripts/peek_cat_exceptions.sh
ci/scripts/peek_cat_queues.sh
ci/scripts/peek_restart_all.sh
ci/scripts/peek_stop_all.sh
ci/scripts/peek_tmux_logs.sh
ci/scripts/peek_watch_all.sh
ci/service/peek_agent.service
ci/service/peek_field.service
ci/service/peek_logic.service
ci/service/peek_office.service
ci/service/peek_worker.service
ci/spec/peek-platform.spec
ci/sudoers.d/peek-platform
config/postgresql/postgresql.conf_16core_32gb_hdd
config/postgresql/postgresql.conf_16core_32gb_ssd
config/postgresql/postgresql.conf_16core_64gb_hdd
config/postgresql/postgresql.conf_16core_64gb_ssd
config/postgresql/postgresql.conf_32core_128gb_hdd
config/postgresql/postgresql.conf_32core_128gb_ssd
config/postgresql/postgresql.conf_4core_8gb_hdd
config/postgresql/postgresql.conf_4core_8gb_ssd
config/postgresql/postgresql.conf_8core_16gb_hdd
config/postgresql/postgresql.conf_8core_16gb_ssd
docs/build_html_docs.sh
docs/build_pdf_doc.sh
docs/conf.py
docs/favicon.ico
docs/guide.rst
docs/index.rst
docs/rtfd_requirements.txt
docs/watch-docs.sh
docs/_static/.gitkeep
docs/administration/admin_config_platform.rst
synerty_peek.egg-info/PKG-INFO
synerty_peek.egg-info/SOURCES.txt
synerty_peek.egg-info/dependency_links.txt
synerty_peek.egg-info/requires.txt
synerty_peek.egg-info/top_level.txt