Metadata-Version: 2.4
Name: synerty-peek
Version: 5.1.4
Summary: Peek Platform - Meta Package to install all services
Author-email: Synerty <contact@synerty.com>
Project-URL: Homepage, https://gitlab.synerty.com/peek/peek
Keywords: Peek,Python,Platform,synerty
Classifier: Programming Language :: Python :: 3.5
License-File: LICENSE.rst
Requires-Dist: peek-admin-doc==5.1.4
Requires-Dist: peek-admin-app==5.1.4
Requires-Dist: peek-agent-service==5.1.4
Requires-Dist: peek-core-device==5.1.4
Requires-Dist: peek-core-docdb==5.1.4
Requires-Dist: peek-core-email==5.1.4
Requires-Dist: peek-core-search==5.1.4
Requires-Dist: peek-core-user==5.1.4
Requires-Dist: peek-core-screen==5.1.4
Requires-Dist: peek-field-doc==5.1.4
Requires-Dist: peek-field-app==5.1.4
Requires-Dist: peek-field-service==5.1.4
Requires-Dist: peek-logic-service==5.1.4
Requires-Dist: peek-office-doc==5.1.4
Requires-Dist: peek-office-app==5.1.4
Requires-Dist: peek-office-service==5.1.4
Requires-Dist: peek-platform==5.1.4
Requires-Dist: peek-plugin-base==5.1.4
Requires-Dist: peek-storage-service==5.1.4
Requires-Dist: peek-worker-service==5.1.4
Requires-Dist: peek-abstract-chunked-index==5.1.4
Requires-Dist: peek-abstract-chunked-data-loader==5.1.4
Requires-Dist: sphinx
Requires-Dist: sphinx-rtd-theme
Requires-Dist: sphinx-autobuild
Requires-Dist: pytmpdir>=1.0.2
Requires-Dist: py-spy
Dynamic: license-file
